parkingfunctions/__init__.py
parkingfunctions/generates.py
parkingfunctions/validate.py
parkingfunctions-0.1.1.dist-info/WHEEL
parkingfunctions-0.1.1.dist-info/METADATA
parkingfunctions-0.1.1.dist-info/RECORD
