Metadata-Version: 2.1
Name: parkingfunctions
Version: 0.1.1
Summary: 
Author: Seth Bangert
Author-email: seth@sbang.me
Requires-Python: >=3.8,<4.0
Classifier: Programming Language :: Python :: 3
Classifier: Programming Language :: Python :: 3.10
Classifier: Programming Language :: Python :: 3.8
Classifier: Programming Language :: Python :: 3.9
Requires-Dist: furo (>=2022.6.21,<2023.0.0)
Requires-Dist: myst-parser (>=0.18.0,<0.19.0)
Requires-Dist: numpy (>=1.23.1,<2.0.0)
Requires-Dist: sphinx-rtd-theme (>=1.0.0,<2.0.0)
